{
  "id": "2bdd0f0a0026807eb615c24a833d0ac6",
  "cat": "ディレクター採用",
  "eyebrow": "HIRING",
  "title": "母集団形成",
  "tags": [],
  "tools": [
    "基本"
  ],
  "content": {
    "基本": "<h3>10秒でわかる！要点まとめ</h3>\n<ul class=\"point-list\">\n<li>「待っている」だけでは来ない。求める人材がいる「場所」へ能動的に出向く</li>\n<li>採用媒体だけでなく、SNSやコミュニティを活用し、潜在層（転職を考えていない人）にアプローチ</li>\n<li>会社の「実態」をオープンにする。ディレクションブログや勉強会が最強の採用コンテンツ</li>\n</ul>\n<h3>1. 概要：求めるターゲット人材に「会社を知ってもらう」活動</h3>\n<p>母集団形成とは、採用要件を満たす見込みのある候補者（ディレクション）に、自社の求人情報を認知させ、応募を促すための一連のマーケティング活動です。</p>\n<p>優秀なディレクションは現職で活躍していることが多く、転職活動をしていません。そのため、一般的な求人媒体に掲載するだけでなく、潜在的な転職者層（潜在層）に対してもリーチし、自社に興味を持ってもらうための「採用ブランディング」と「チャネル設計」が求められます。この活動の規模と質が、その後の採用成功率を決定づけます。</p>\n<h3>2. なぜ重要なのか：優秀な人材は「競合」と取り合いになる</h3>\n<p>Webディレクションは市場価値が高く、どの企業も優秀な人材を求めているため、人材獲得競争（タレント・アクイジション）は激化しています。応募者がゼロ、あるいは自社の要件に合わない人ばかり集まる状況では、どれだけ面接スキルが高くても採用は成功しません。</p>\n<p>母集団形成を強化することは、「選ぶ側」の選択肢を増やすだけでなく、自社の理念や働き方を事前に伝えることで、入社後のミスマッチを最小限に抑える効果もあります。</p>\n<h3>3. 実務のポイント：チャネル設計とコンテンツ戦略</h3>\n<p>実務では、一つのチャネルに頼らず、複数の経路（チャネル）から多角的にアプローチする戦略が必要です。</p>\n<ul class=\"point-list\">\n<li>チャネルの多角化：</li>\n<li>顕在層（今すぐ転職したい人）：転職エージェント、大手求人媒体。</li>\n<li>準顕在層（良い案件があれば検討する人）：スカウト型SNS（Wantedly、LinkedIn）、ダイレクトリクルーティング。</li>\n<li>潜在層（今は転職を考えていない人）：ディレクション向け技術ブログ、業界勉強会への登壇、ミートアップ開催。</li>\n<li>「働く人」の顔出し：求人票だけでは伝わらない、「一緒に働くディレクションの魅力」をコンテンツ化します。社員インタビュー記事、リモートワーク環境の紹介、普段使用しているツールの紹介記事などは、現場のリアルな雰囲気を伝える最強のコンテンツになります。</li>\n<li>リファラル（社員紹介）の仕組み化：すでに自社で活躍しているディレクションからの紹介は、カルチャーマッチの確率が非常に高いです。社員が「この会社で働くのは楽しい」と自信を持って言える環境を作り、紹介インセンティブや仕組みを整備することが効果的です。</li>\n</ul>\n<h3>4. スキルアップのヒント：コミュニティへの貢献意識を持つ</h3>\n<p>業界コミュニティや勉強会に「求職者」としてではなく、「情報提供者・貢献者」として参加する意識を持つことです。イベントに登壇したり、ノウハウを共有したりすることで、「あの会社の人、いつも良い話をしてくれるな」という形で企業への好感度が高まり、それが長期的な採用ブランディングに繋がります。</p>\n<p>また、ダイレクトスカウトを行う際には、「定型文」ではなく、応募者の過去の経歴や発信内容を読み込んだ上で、「なぜあなたに声をかけたのか」を具体的に記載することで、返信率が格段に向上します。</p>"
  }
}
